sqlalchemy_dst/__init__.py
sqlalchemy_dst/sqlalchemy_dst.py
sqlalchemy_dst-1.0.1.dist-info/DESCRIPTION.rst
sqlalchemy_dst-1.0.1.dist-info/METADATA
sqlalchemy_dst-1.0.1.dist-info/RECORD
sqlalchemy_dst-1.0.1.dist-info/WHEEL
sqlalchemy_dst-1.0.1.dist-info/metadata.json
sqlalchemy_dst-1.0.1.dist-info/top_level.txt
tests/__init__.py
tests/config.py
tests/main.py
tests/schema.py
tests/test.py
tests/unit/__init__.py
tests/unit/test_dict2row.py
tests/unit/test_model.py
tests/unit/test_row2dict.py
