Metadata-Version: 2.0
Name: sqlalchemy-dst
Version: 1.0.1
Summary: SQLAlchemy Dictionary Serialization Tools.
Home-page: https://github.com/yarbshk/sqlalchemy-dst
Author: Yuriy Rabeshko
Author-email: george.rabeshko@gmail.com
License: MIT
Keywords: sqlalchemy python dict serialize tool
Platform: UNKNOWN
Classifier: Development Status :: 4 - Beta
Classifier: Intended Audience :: Developers
Classifier: License :: OSI Approved :: MIT License
Classifier: Natural Language :: English
Classifier: Programming Language :: Python
Classifier: Topic :: Software Development :: Libraries :: Python Modules
Requires-Dist: sqlalchemy (>=0.9.4)
